setup.py
pysvtools/__init__.py
pysvtools/merge.py
pysvtools/mergefaster.py
pysvtools/utils.py
pysvtools.egg-info/PKG-INFO
pysvtools.egg-info/SOURCES.txt
pysvtools.egg-info/dependency_links.txt
pysvtools.egg-info/entry_points.txt
pysvtools.egg-info/requires.txt
pysvtools.egg-info/top_level.txt
pysvtools/models/__init__.py
pysvtools/models/event.py
pysvtools/models/exclusionregion.py
pysvtools/models/intersection.py