Metadata-Version: 1.1
Name: pysvtools
Version: 0.1.3
Summary: VCF toolkit for SV analysis
Home-page: https://github.com/wyleung/pySVtools
Author: LUMC, Wai Yi Leung
Author-email: w.y.leung@lumc.nl
License: MIT License
Keywords: bioinformatics
Platform: any
Classifier: Development Status :: 4 - Beta
Classifier: Intended Audience :: Science/Research
Classifier: Intended Audience :: Developers
Classifier: Operating System :: OS Independent
Classifier: Programming Language :: Python
Classifier: Topic :: Scientific/Engineering
